README.md
setup.py
ICE/__init__.py
akilan.egg-info/PKG-INFO
akilan.egg-info/SOURCES.txt
akilan.egg-info/dependency_links.txt
akilan.egg-info/top_level.txt