Metadata-Version: 2.1
Name: akilan
Version: 0.0.2
Summary: Image classification engine
Home-page: UNKNOWN
Author: Akilan km
License: UNKNOWN
Platform: UNKNOWN
Classifier: Programming Language :: Python :: 3
Classifier: License :: OSI Approved :: MIT License
Classifier: Operating System :: OS Independent
Requires-Python: >=3.6
